Metadata-Version: 2.1
Name: gunicorn-pipe
Version: 19.10.1
Summary: Gunicorn with concurrent support for HTTP Pipeline requests
Home-page: UNKNOWN
Author: carton.swing
Author-email: carton.swing@gmail.com
License: MIT
Platform: UNKNOWN
Classifier: Development Status :: 4 - Beta
Classifier: Environment :: Other Environment
Classifier: Intended Audience :: Developers
Classifier: License :: OSI Approved :: MIT License
Classifier: Operating System :: MacOS :: MacOS X
Classifier: Operating System :: POSIX
Classifier: Programming Language :: Python
Classifier: Programming Language :: Python :: 2
Classifier: Programming Language :: Python :: 2.6
Classifier: Programming Language :: Python :: 2.7
Classifier: Programming Language :: Python :: 3
Classifier: Programming Language :: Python :: 3.2
Classifier: Programming Language :: Python :: 3.3
Classifier: Programming Language :: Python :: 3.4
Classifier: Programming Language :: Python :: 3.5
Classifier: Programming Language :: Python :: 3.6
Classifier: Programming Language :: Python :: 3.7
Classifier: Topic :: Internet
Classifier: Topic :: Utilities
Classifier: Topic :: Software Development :: Libraries :: Python Modules
Classifier: Topic :: Internet :: WWW/HTTP
Classifier: Topic :: Internet :: WWW/HTTP :: WSGI
Classifier: Topic :: Internet :: WWW/HTTP :: WSGI :: Server
Classifier: Topic :: Internet :: WWW/HTTP :: Dynamic Content
Requires-Python: >=2.6, !=3.0.*, !=3.1.*
Provides-Extra: eventlet
Requires-Dist: eventlet (>=0.9.7) ; extra == 'eventlet'
Provides-Extra: gevent
Requires-Dist: gevent (>=0.13) ; extra == 'gevent'
Provides-Extra: gthread
Provides-Extra: tornado
Requires-Dist: tornado (>=0.2) ; extra == 'tornado'
